cjudge/__init__.py
cjudge/config.py
cjudge/error.py
cjudge/problem.py
cjudge/terminal_utils.py
cjudge/tester.py
cjudge/config/config.json
cjudge/config/template.cpp
cjudge/judges/aceptaelreto.py
cjudge/judges/judge.py
cjudge/judges/kattis.py
cjudge/judges/nonejudge.py
cjudge/judges/uva.py
cjudge/scripts/create.py
cjudge/scripts/info.py
cjudge/scripts/submit.py
cjudge/scripts/test.py
cjudge-1.0.0.dist-info/METADATA
cjudge-1.0.0.dist-info/WHEEL
cjudge-1.0.0.dist-info/entry_points.txt
cjudge-1.0.0.dist-info/licenses/LICENSE
cjudge-1.0.0.dist-info/RECORD
