Metadata-Version: 2.3
Name: cjudge
Version: 1.0.0
Summary: CLI utility for different online judges.
Project-URL: Homepage, https://github.com/NotTete/cjudge
Author-email: Jorge Hdez <jorgehdezplp@proton.me>
License-File: LICENSE
Classifier: License :: OSI Approved :: MIT License
Classifier: Programming Language :: Python :: 3
Requires-Python: >=3.8
Requires-Dist: bs4
Requires-Dist: kattispdf
Requires-Dist: requests
